asynchw.py
asynchw-0.0.1.dist-info/WHEEL
asynchw-0.0.1.dist-info/METADATA
asynchw-0.0.1.dist-info/RECORD
