Metadata-Version: 2.1
Name: asynchw
Version: 0.0.1
Summary: More stuff coming
Author: Olli Paloviita
